create_claude_app/__init__.py
create_claude_app/cli.py
create_claude_app/file_operations.py
create_claude_app/generators.py
create_claude_app/prompts.py
create_claude_app/validators.py
create_claude_app/templates/README.md
create_claude_app-0.4.1.dist-info/licenses/LICENSE
create_claude_app-0.4.1.dist-info/METADATA
create_claude_app-0.4.1.dist-info/WHEEL
create_claude_app-0.4.1.dist-info/entry_points.txt
create_claude_app-0.4.1.dist-info/top_level.txt
create_claude_app-0.4.1.dist-info/RECORD
