Metadata-Version: 2.4
Name: create-claude-app
Version: 0.4.1
Summary: Interactive Python CLI tool that scaffolds new projects optimized for Claude Code development
Author-email: Wen-Hsiang Shih <swh@hsiang.io>
License: MIT License
Project-URL: Homepage, https://github.com/swhsiang/create-claude-app
Project-URL: Issues, https://github.com/swhsiang/create-claude-app/issues
Classifier: Development Status :: 3 - Alpha
Classifier: Intended Audience :: Developers
Classifier: Programming Language :: Python :: 3
Classifier: Programming Language :: Python :: 3.8
Classifier: Programming Language :: Python :: 3.9
Classifier: Programming Language :: Python :: 3.10
Classifier: Programming Language :: Python :: 3.11
Classifier: Programming Language :: Python :: 3.12
Requires-Python: >=3.8
License-File: LICENSE
Requires-Dist: click>=8.0.0
Requires-Dist: rich>=13.0.0
Requires-Dist: jinja2>=3.0.0
Requires-Dist: colorama>=0.4.0
Provides-Extra: dev
Requires-Dist: pytest>=7.0.0; extra == "dev"
Requires-Dist: pytest-cov>=4.0.0; extra == "dev"
Requires-Dist: black>=22.0.0; extra == "dev"
Requires-Dist: flake8>=5.0.0; extra == "dev"
Requires-Dist: mypy>=1.0.0; extra == "dev"
Requires-Dist: pre-commit>=3.0.0; extra == "dev"
Dynamic: license-file
